divinegift/__init__.py
divinegift/aims.py
divinegift/app.py
divinegift/banner.py
divinegift/cipher.py
divinegift/config.py
divinegift/db.py
divinegift/errors.py
divinegift/excel.py
divinegift/kafka_client.py
divinegift/kthreads.py
divinegift/logger.py
divinegift/mailer.py
divinegift/main.py
divinegift/sender.py
divinegift/smb.py
divinegift/string_avro.py
divinegift/telegram.py
divinegift/templator.py
divinegift/timer.py
divinegift/translit.py
divinegift/zabbix_agent.py
divinegift-2.15.22.dist-info/METADATA
divinegift-2.15.22.dist-info/WHEEL
divinegift-2.15.22.dist-info/top_level.txt
divinegift-2.15.22.dist-info/RECORD
