Metadata-Version: 2.1
Name: divinegift
Version: 2.15.22
Summary: Ver.2.15.20. Config not necessary for Application.
Home-page: https://gitlab.com/gng-group/divinegift.git
Author: Malanris
Author-email: admin@malanris.ru
License: MIT
Classifier: Development Status :: 5 - Production/Stable
Classifier: License :: OSI Approved :: MIT License
Classifier: License :: OSI Approved :: Apache Software License
Classifier: Programming Language :: Python :: 3
Classifier: Operating System :: OS Independent
Requires-Dist: requests >=2.23.0
Requires-Dist: deprecation >=2.1.0
Requires-Dist: cryptography >=2.9.2
Requires-Dist: pyyaml >=5.1
Requires-Dist: python-dateutil >=2.8.1
Requires-Dist: schedule ==1.1.0
